README.txt
sc-releaser.cfg
setup.cfg
setup.py
docs/HISTORY.txt
docs/INSTALL.txt
docs/LICENSE.GPL
docs/LICENSE.txt
sc/__init__.py
sc.base.hotsites.egg-info/PKG-INFO
sc.base.hotsites.egg-info/SOURCES.txt
sc.base.hotsites.egg-info/dependency_links.txt
sc.base.hotsites.egg-info/entry_points.txt
sc.base.hotsites.egg-info/namespace_packages.txt
sc.base.hotsites.egg-info/not-zip-safe
sc.base.hotsites.egg-info/paster_plugins.txt
sc.base.hotsites.egg-info/requires.txt
sc.base.hotsites.egg-info/top_level.txt
sc/base/__init__.py
sc/base/hotsites/README.txt
sc/base/hotsites/__init__.py
sc/base/hotsites/config.py
sc/base/hotsites/configure.zcml
sc/base/hotsites/interfaces.py
sc/base/hotsites/skins.zcml
sc/base/hotsites/subscribers.py
sc/base/hotsites/tests.py
sc/base/hotsites/version.txt
sc/base/hotsites/adapters/__init__.py
sc/base/hotsites/adapters/hotsites.py
sc/base/hotsites/browser/__init__.py
sc/base/hotsites/browser/configure.zcml
sc/base/hotsites/controlpanel/__init__.py
sc/base/hotsites/controlpanel/configure.zcml
sc/base/hotsites/controlpanel/hotsites.py
sc/base/hotsites/docs/__init__.py
sc/base/hotsites/docs/browser.txt
sc/base/hotsites/locales/manual.pot
sc/base/hotsites/locales/rebuildAll.sh
sc/base/hotsites/locales/sc.base.hotsites.pot
sc/base/hotsites/locales/scbasehotsites.pot
sc/base/hotsites/locales/pt_BR/LC_MESSAGES/sc.base.hotsites.po
sc/base/hotsites/profiles/default/controlpanel.xml
sc/base/hotsites/profiles/default/metadata.xml
sc/base/hotsites/profiles/default/propertiestool.xml
sc/base/hotsites/profiles/default/skins.xml
sc/base/hotsites/profiles/default/unused_registry.xml
sc/base/hotsites/profiles/default/viewlets.xml
sc/base/hotsites/skins/sc_hotsite_skin/flashmovie_view.pt
sc/base/hotsites/skins/sc_hotsite_skin/ministio_place_holder.swf